bin/__init__.py
bin/activate_this.py
bin/epsg_tr.py
bin/esri2wkt.py
bin/gcps2vec.py
bin/gcps2wld.py
bin/gdal2tiles.py
bin/gdal2xyz.py
bin/gdal_auth.py
bin/gdal_calc.py
bin/gdal_edit.py
bin/gdal_fillnodata.py
bin/gdal_merge.py
bin/gdal_pansharpen.py
bin/gdal_polygonize.py
bin/gdal_proximity.py
bin/gdal_retile.py
bin/gdal_sieve.py
bin/gdalchksum.py
bin/gdalcompare.py
bin/gdalident.py
bin/gdalimport.py
bin/gdalmove.py
bin/index.py
bin/mkgraticule.py
bin/ogrmerge.py
bin/pct2rgb.py
bin/rgb2pct.py
mfd/__init__.py
mfd/debug.py
mfd/gtif.py
mfd/hydrogram.py
mfd/index.py
mfd/matrix.py
mfdfloods/__init__.py
mfdfloods/debug.py
mfdfloods/geotransform.py
mfdfloods/gtif.py
mfdfloods/hydrogram.py
mfdfloods/index.py
mfdfloods/matrix.py
MFD_Floods-0.1.14.dist-info/METADATA
MFD_Floods-0.1.14.dist-info/WHEEL
MFD_Floods-0.1.14.dist-info/top_level.txt
MFD_Floods-0.1.14.dist-info/RECORD
