Metadata-Version: 2.1
Name: MFD-Floods
Version: 0.1.14
Summary: A python script to modelate hidrologic behavior of downstream drainpaths
Home-page: https://github.com/orzocogorzo/mfdfloods
Author: Orzo Cogorzo
Author-email: orzocogorzo@hotmail.com
License: MIT
Keywords: mfdfloods mfd flood drainpaths hidrology downstreams multiple flow direction
Platform: UNKNOWN
Classifier: Development Status :: 3 - Alpha
Classifier: Environment :: Console
Classifier: Intended Audience :: Science/Research
Classifier: Programming Language :: Python :: 3
Classifier: License :: OSI Approved :: MIT License
Classifier: Operating System :: OS Independent
Classifier: Topic :: Scientific/Engineering :: Hydrology
Requires-Dist: GDAL
Requires-Dist: numpy
Requires-Dist: richdem
